{"skeleton":{"hash":"b6Pi8XXeHw1u8U1WG4EoNY08EY4","spine":"3.8.96","x":-467.49,"y":-241.19,"width":487,"height":504},"bones":[{"name":"root"},{"name":"bone","parent":"root"},{"name":"bone2","parent":"bone"},{"name":"bone3","parent":"bone"},{"name":"bone4","parent":"bone"},{"name":"bone5","parent":"bone"},{"name":"bone6","parent":"bone"},{"name":"bone7","parent":"bone","x":0.32},{"name":"bone8","parent":"root","x":151.29,"y":185.35},{"name":"bone9","parent":"root","x":236.68,"y":96.83},{"name":"bone10","parent":"root","x":241.85,"y":33.97},{"name":"bone11","parent":"root","x":246.15,"y":-27.16},{"name":"bone12","parent":"root","x":248.74,"y":-81.4},{"name":"bone13","parent":"root","x":242.71,"y":-144.25}],"slots":[{"name":"burst1","bone":"bone2","attachment":"burst1"},{"name":"burst2","bone":"bone3","attachment":"burst2"},{"name":"burst3","bone":"bone4","attachment":"burst3"},{"name":"burst4","bone":"bone5","attachment":"burst4"},{"name":"burst5","bone":"bone6","attachment":"burst5"},{"name":"particle","bone":"bone7","color":"007effff","attachment":"particle","blend":"screen"}],"transform":[{"name":"burst1","order":1,"bones":["bone2"],"target":"bone9","x":-254.37,"y":-107.08,"rotateMix":0,"translateMix":0},{"name":"burst2","order":2,"bones":["bone3"],"target":"bone10","x":-292.3,"y":-44.22,"rotateMix":0,"translateMix":0},{"name":"burst3","order":3,"bones":["bone4"],"target":"bone11","x":-327.81,"y":16.91,"rotateMix":0,"translateMix":0},{"name":"burst4","order":4,"bones":["bone5"],"target":"bone12","x":-364.71,"y":71.15,"rotateMix":0,"translateMix":0},{"name":"burst5","order":5,"bones":["bone6"],"target":"bone13","x":-388.43,"y":134,"rotateMix":0,"translateMix":0},{"name":"particle_rem","bones":["bone7"],"target":"bone8","x":-198.33,"y":-0.15,"rotateMix":0,"translateMix":0}],"skins":[{"name":"default","attachments":{"burst1":{"burst1":{"x":-215.98,"y":9.81,"width":471,"height":480}},"burst2":{"burst2":{"x":-212.49,"y":10.81,"width":464,"height":504}},"burst3":{"burst3":{"x":-206.49,"y":18.81,"width":450,"height":462}},"burst4":{"burst4":{"x":-320.49,"y":12.31,"width":222,"height":351}},"burst5":{"burst5":{"x":-306.99,"y":4.81,"width":211,"height":182}},"particle":{"particle":{"x":-228.81,"y":6.31,"width":478,"height":459}}}}],"animations":{"animation":{"slots":{"burst1":{"attachment":[{"name":"burst1"},{"time":0.0333,"name":null}]},"burst2":{"attachment":[{"name":null},{"time":0.0333,"name":"burst2"},{"time":0.0667,"name":null}]},"burst3":{"attachment":[{"name":null},{"time":0.0667,"name":"burst3"},{"time":0.1,"name":null}]},"burst4":{"attachment":[{"name":null},{"time":0.1,"name":"burst4"},{"time":0.1333,"name":null}]},"burst5":{"color":[{"time":0.1333,"color":"ffffffff","curve":0.521,"c3":0.551},{"time":0.1833,"color":"ffffff00"}],"attachment":[{"name":null},{"time":0.1333,"name":"burst5"}]},"particle":{"color":[{"color":"007effff","curve":"stepped"},{"time":0.0333,"color":"007effff","curve":0.1,"c2":0.34,"c3":0.589,"c4":0.79},{"time":0.25,"color":"007eff00"}],"attachment":[{"name":"particle"}]}},"bones":{"bone8":{"scale":[{"x":0.896,"y":0.896,"curve":0,"c2":0.57,"c3":0.551},{"time":0.25,"x":2.223,"y":2.223}]},"bone":{"translate":[{}],"scale":[{"x":0.805,"y":0.805,"curve":0.004,"c2":0.65,"c3":0.551},{"time":0.1,"x":1.745,"y":1.745}]}},"transform":{"burst1":[{"rotateMix":0,"translateMix":0,"scaleMix":0,"shearMix":0}],"burst2":[{"rotateMix":0,"translateMix":0,"scaleMix":0,"shearMix":0}],"burst3":[{"rotateMix":0,"translateMix":0,"scaleMix":0,"shearMix":0}],"burst4":[{"rotateMix":0,"translateMix":0,"scaleMix":0,"shearMix":0}],"burst5":[{"rotateMix":0,"translateMix":0,"scaleMix":0,"shearMix":0}],"particle_rem":[{"rotateMix":0,"translateMix":0,"shearMix":0}]}}}}